quietex/__init__.py
quietex/__main__.py
quietex/_meta.py
quietex/cli.py
quietex/formatter.py
quietex/frontend.py
quietex/latexmkrc
quietex/lexer.py
quietex/status.py
quietex-0.2.0.dist-info/METADATA
quietex-0.2.0.dist-info/WHEEL
quietex-0.2.0.dist-info/entry_points.txt
quietex-0.2.0.dist-info/top_level.txt
quietex-0.2.0.dist-info/zip-safe
quietex-0.2.0.dist-info/RECORD
