Metadata-Version: 2.1
Name: quietex
Version: 0.2.0
Summary: Filter output of pdflatex.
Home-page: https://github.com/mje-nz/quietex
Author: Matthew Edwards
License: BSD 3-Clause
Platform: UNKNOWN
Classifier: Development Status :: 3 - Alpha
Classifier: Intended Audience :: Science/Research
Classifier: License :: OSI Approved :: BSD License
Classifier: Operating System :: MacOS :: MacOS X
Classifier: Operating System :: POSIX :: Linux
Classifier: Programming Language :: Python :: 3
Classifier: Programming Language :: Python :: 3.7
Classifier: Programming Language :: Python :: 3.8
Classifier: Programming Language :: Python :: 3.9
Classifier: Topic :: Text Processing :: Markup :: LaTeX
Requires-Python: >=3.7
Requires-Dist: attrs
Requires-Dist: blessings
Requires-Dist: pexpect
Requires-Dist: pygments
Provides-Extra: test
Requires-Dist: pyte ; extra == 'test'
Requires-Dist: pytest ; extra == 'test'
Requires-Dist: pytest-cov ; extra == 'test'
